<?xml version="1.0" encoding="UTF-8"?>
<!DOCTYPE mapper PUBLIC "-//mybatis.org//DTD Mapper 3.0//EN" 
"http://mybatis.org/dtd/mybatis-3-mapper.dtd">
<mapper namespace="com.billmanager.jizhang.mapper.IncomeCategoryMapper">

    <resultMap id="BaseResultMap" type="com.billmanager.jizhang.entity.IncomeCategory">
        <id column="id" property="id"/>
        <result column="user_id" property="userId"/>
        <result column="family_group_id" property="familyGroupId"/>
        <result column="name" property="name"/>
        <result column="description" property="description"/>
        <result column="create_time" property="createTime"/>
        <result column="update_time" property="updateTime"/>
    </resultMap>

    <insert id="insert" parameterType="com.billmanager.jizhang.entity.IncomeCategory" useGeneratedKeys="true" keyProperty="id">
        INSERT INTO income_category (user_id, family_group_id, name, description, is_built_in, create_time, update_time)
        VALUES (#{userId}, #{familyGroupId}, #{name}, #{description}, #{isBuiltIn}, #{createTime}, #{updateTime})
    </insert>

    <update id="update" parameterType="com.billmanager.jizhang.entity.IncomeCategory">
        UPDATE income_category
        <set>
            <if test="name != null">name = #{name},</if>
            <if test="description != null">description = #{description},</if>
            update_time = CURRENT_TIMESTAMP
        </set>
        WHERE id = #{id}
    </update>

    <delete id="deleteById">
        DELETE FROM income_category WHERE id = #{id}
    </delete>

    <select id="findById" resultMap="BaseResultMap">
        SELECT * FROM income_category WHERE id = #{id}
    </select>

    <select id="findByUserId" resultMap="BaseResultMap">
        SELECT * FROM income_category WHERE user_id = #{userId} ORDER BY create_time DESC
    </select>

    <select id="findByUserIdAndName" resultMap="BaseResultMap">
        SELECT * FROM income_category 
        WHERE user_id = #{userId} 
        AND name = #{name}
    </select>

    <!-- 按家庭组查询 -->
    <select id="findByFamilyGroupId" resultMap="BaseResultMap">
        SELECT * FROM income_category WHERE family_group_id = #{familyGroupId} ORDER BY create_time DESC
    </select>

    <select id="findByFamilyGroupIdAndName" resultMap="BaseResultMap">
        SELECT * FROM income_category 
        WHERE family_group_id = #{familyGroupId} 
        AND name = #{name}
    </select>

    <!-- 更新指定用户的所有分类的家庭组ID -->
    <update id="updateFamilyGroupId">
        UPDATE income_category 
        SET family_group_id = #{familyGroupId}, update_time = CURRENT_TIMESTAMP
        WHERE user_id = #{userId}
    </update>

    <!-- 删除指定用户的所有分类 -->
    <delete id="deleteByUserId">
        DELETE FROM income_category WHERE user_id = #{userId} AND is_built_in = 0
    </delete>
    
    <!-- 删除指定用户在指定家族组中的分类 -->
    <delete id="deleteByUserIdAndFamilyGroupId">
        DELETE FROM income_category WHERE user_id = #{userId} AND family_group_id = #{familyGroupId}
    </delete>
    
    <!-- 将指定用户在指定家族组中的分类转换为个人数据，不转换系统内置分类 -->
    <update id="updateFamilyGroupIdToPersonal">
        UPDATE income_category 
        SET family_group_id = 0, update_time = CURRENT_TIMESTAMP
        WHERE user_id = #{userId} AND family_group_id = #{familyGroupId} AND is_built_in = 0
    </update>
    
    <!-- 更新指定用户的所有非系统内置分类的家庭组ID -->
    <update id="updateFamilyGroupIdExcludeBuiltIn">
        UPDATE income_category 
        SET family_group_id = #{familyGroupId}, update_time = CURRENT_TIMESTAMP
        WHERE user_id = #{userId} AND is_built_in = 0
    </update>

</mapper>
